ServiceRX/__init__.py
ServiceRX/auth/__init__.py
ServiceRX/client/__init__.py
ServiceRX/controller/__init__.py
ServiceRX/examples/__init__.py
ServiceRX/examples/client.py
ServiceRX/examples/controller.py
ServiceRX/objects/__init__.py
ServiceRX/objects/request_objects.py
ServiceRX-0.0.1.dist-info/LICENSE
ServiceRX-0.0.1.dist-info/METADATA
ServiceRX-0.0.1.dist-info/WHEEL
ServiceRX-0.0.1.dist-info/top_level.txt
ServiceRX-0.0.1.dist-info/RECORD
